multiplicador_somador.v
module multiplicador_somador(
    input  [15:0] a,
    input  [15:0] b,
    input h,
    output  [15:0] out
);

    assign out = h? a * b : a + b;

endmodule

mux.v
module mux(
    input signed [15:0] a,
    input signed [15:0] b,
    input signed [15:0] c,
    input signed [15:0] d,
    input  [1:0] set,
    output signed [15:0] out
);
    assign out = set == 0 ? a : set == 1 ? b : set == 2 ? c : d; 

endmodule

registrador.v
module registrador(
    input clk,
    input l,
    input signed [15:0] in,
    output reg signed [15:0] out
);

    always @(posedge clk) begin
        if (l == 1) begin
            out <= in;
        end
    end

endmodule

bo_bc.v
`include "registrador.v"
`include "mux.v"
`include "multiplicador_somador.v"

module bo(
    input clock,
    input LX,
    input [1:0] M0,
    input [1:0] M1,
    input [1:0] M2,
    input H,
    input LS,
    input LH,
    input  [7:0] valor_x,
    input  [15:0] valor_a,
    input  [15:0] valor_b,
    input  [15:0] valor_c,
    output  [15:0] resultado
);
    wire  [15:0] valor_x16;
    assign valor_x16 = valor_x;
    wire  [15:0] out_x;
    wire  [15:0] out_s;
    wire  [15:0] out_h;
    wire  [15:0] out_mux0;
    wire  [15:0] out_mux1;
    wire  [15:0] out_mux2;
    wire  [15:0] out_ula;

    registrador reg_x(clock, LX, valor_x16, out_x);
    registrador reg_s(clock, LS, out_ula, out_s);
    registrador reg_h(clock, LH, out_ula, out_h);

    mux mux0(valor_a,valor_a,valor_b,valor_c,M0,out_mux0);
    mux mux1(out_mux0,out_x,out_s, out_h, M1, out_mux1);
    mux mux2(out_x, out_mux0, out_s, out_h, M2, out_mux2);

    multiplicador_somador multiplicador_somador0(out_mux1, out_mux2, H, out_ula);

    assign resultado = out_s;

endmodule

module bc(
    input clock,
    input reset,
    input enable,
    output LX,
    output [1:0] M0,
    output [1:0] M1,
    output [1:0] M2,
    output H,
    output LS,
    output LH,
    output done,
    output ready
);
    reg[3:0] state;

    always @(posedge clock or reset) begin

        if (reset)
            state <= 0;

        else begin
            if (state == 0 && ~enable)
                state <= state;
            else begin
                if(state == 8)
                    state <= 0;
                else begin
                state <= state + 1;
                end
            end
        end
    end

    assign M0 = state == 0? 0 : state == 3? 1 : state == 4? 2 : state == 6? 3 : 0;

    assign M1 = state == 2? 1 : state == 3? 0 :  state == 5? 2 : state == 6? 0 : 0;

    assign M2 = state == 2? 0 : state == 3? 2 :  state == 5? 3 : state == 6? 3 : 0;

    assign H = state == 2? 1 : state == 3? 1 : state == 4? 1 : 0;

    assign LX = state == 1? 1 : 0;

    assign LS = state == 2? 1 : state == 4? 1 : state == 6? 1 : 0;

    assign LH = state == 3? 1 : state == 5? 1 : 0;

    assign done = state == 0? 0 : state == 1? 0 : state == 2? 0 : state == 3? 0 : state == 4? 0 : state == 5? 0 : state == 6? 0 : state == 7? 1 : 0;

    assign ready = state == 0? 1 : state == 1? 0 : state == 2? 0 : state == 3? 0 : state == 4? 0 : state == 5? 0 : state == 6? 0 : state == 7? 0 : 0;

endmodule

testebench.v
`include "bo_bc.v"

module ula(
    input clock,
    input  [7:0] valor_x,
    input  [15:0] valor_a,
    input  [15:0] valor_b,
    input  [15:0] valor_c,
    input enable,
    input reset,
    output  [15:0] result,
    output ready,
    output valid
);
    wire LX;
    wire [1:0] M0;
    wire [1:0] M1;
    wire [1:0] M2;
    wire H;
    wire LS;
    wire LH;

    bc bc0(clock, reset, enable, LX, M0, M1, M2, H, LS, LH, valid, ready);
    bo bo0(clock, LX, M0, M1, M2, H, LS, LH, valor_x, valor_a, valor_b, valor_c, result);

endmodule

module testbench;

	reg  [7:0] x = 3;
	reg  [15:0] a = 3;
	reg  [15:0] b = 3;
	reg  [15:0] c = 3;
	wire  [15:0] resultado;

	reg clock = 0, enable = 0, reset = 0;

	wire valid, ready;


	ula ula0(clock, x, a, b, c, enable, reset, resultado, ready, valid);

	always #1 clock <= ~clock;


	initial begin
	    $dumpvars;
	    
	    reset <= 1;

	    #1;

	    reset <= 0;
	    enable <= 1;

	    #13
	    $finish;
	end

endmodule

dump.vcd
$date
	Thu May 13 21:04:23 2021
$end
$version
	Icarus Verilog
$end
$timescale
	1s
$end
$scope module testbench $end
$var wire 1 ! valid $end
$var wire 16 " resultado [15:0] $end
$var wire 1 # ready $end
$var reg 16 $ a [15:0] $end
$var reg 16 % b [15:0] $end
$var reg 16 & c [15:0] $end
$var reg 1 ' clock $end
$var reg 1 ( enable $end
$var reg 1 ) reset $end
$var reg 8 * x [7:0] $end
$scope module ula0 $end
$var wire 1 ' clock $end
$var wire 1 ( enable $end
$var wire 1 ) reset $end
$var wire 16 + valor_a [15:0] $end
$var wire 16 , valor_b [15:0] $end
$var wire 16 - valor_c [15:0] $end
$var wire 8 . valor_x [7:0] $end
$var wire 1 ! valid $end
$var wire 16 / result [15:0] $end
$var wire 1 # ready $end
$var wire 2 0 M2 [1:0] $end
$var wire 2 1 M1 [1:0] $end
$var wire 2 2 M0 [1:0] $end
$var wire 1 3 LX $end
$var wire 1 4 LS $end
$var wire 1 5 LH $end
$var wire 1 6 H $end
$scope module bc0 $end
$var wire 1 ' clock $end
$var wire 1 ( enable $end
$var wire 1 ) reset $end
$var wire 1 # ready $end
$var wire 1 ! done $end
$var wire 2 7 M2 [1:0] $end
$var wire 2 8 M1 [1:0] $end
$var wire 2 9 M0 [1:0] $end
$var wire 1 3 LX $end
$var wire 1 4 LS $end
$var wire 1 5 LH $end
$var wire 1 6 H $end
$var reg 4 : state [3:0] $end
$upscope $end
$scope module bo0 $end
$var wire 1 6 H $end
$var wire 1 5 LH $end
$var wire 1 4 LS $end
$var wire 1 3 LX $end
$var wire 2 ; M0 [1:0] $end
$var wire 2 < M1 [1:0] $end
$var wire 2 = M2 [1:0] $end
$var wire 1 ' clock $end
$var wire 16 > resultado [15:0] $end
$var wire 16 ? valor_a [15:0] $end
$var wire 16 @ valor_b [15:0] $end
$var wire 16 A valor_c [15:0] $end
$var wire 8 B valor_x [7:0] $end
$var wire 16 C valor_x16 [15:0] $end
$var wire 16 D out_x [15:0] $end
$var wire 16 E out_ula [15:0] $end
$var wire 16 F out_s [15:0] $end
$var wire 16 G out_mux2 [15:0] $end
$var wire 16 H out_mux1 [15:0] $end
$var wire 16 I out_mux0 [15:0] $end
$var wire 16 J out_h [15:0] $end
$scope module multiplicador_somador0 $end
$var wire 1 6 h $end
$var wire 16 K out [15:0] $end
$var wire 16 L b [15:0] $end
$var wire 16 M a [15:0] $end
$upscope $end
$scope module mux0 $end
$var wire 16 N a [15:0] $end
$var wire 16 O b [15:0] $end
$var wire 16 P c [15:0] $end
$var wire 16 Q d [15:0] $end
$var wire 2 R set [1:0] $end
$var wire 16 S out [15:0] $end
$upscope $end
$scope module mux1 $end
$var wire 16 T a [15:0] $end
$var wire 2 U set [1:0] $end
$var wire 16 V out [15:0] $end
$var wire 16 W d [15:0] $end
$var wire 16 X c [15:0] $end
$var wire 16 Y b [15:0] $end
$upscope $end
$scope module mux2 $end
$var wire 16 Z b [15:0] $end
$var wire 2 [ set [1:0] $end
$var wire 16 \ out [15:0] $end
$var wire 16 ] d [15:0] $end
$var wire 16 ^ c [15:0] $end
$var wire 16 _ a [15:0] $end
$upscope $end
$scope module reg_h $end
$var wire 1 ' clk $end
$var wire 16 ` in [15:0] $end
$var wire 1 5 l $end
$var reg 16 a out [15:0] $end
$upscope $end
$scope module reg_s $end
$var wire 1 ' clk $end
$var wire 16 b in [15:0] $end
$var wire 1 4 l $end
$var reg 16 c out [15:0] $end
$upscope $end
$scope module reg_x $end
$var wire 1 ' clk $end
$var wire 16 d in [15:0] $end
$var wire 1 3 l $end
$var reg 16 e out [15:0] $end
$upscope $end
$upscope $end
$upscope $end
$upscope $end
$enddefinitions $end
#0
$dumpvars
bx e
b11 d
bx c
bx b
bx a
bx `
bx _
bx ^
bx ]
bx \
b0 [
b11 Z
bx Y
bx X
bx W
b11 V
b0 U
b11 T
b11 S
b0 R
b11 Q
b11 P
b11 O
b11 N
b11 M
bx L
bx K
bx J
b11 I
b11 H
bx G
bx F
bx E
bx D
b11 C
b11 B
b11 A
b11 @
b11 ?
bx >
b0 =
b0 <
b0 ;
b0 :
b0 9
b0 8
b0 7
06
05
04
03
b0 2
b0 1
b0 0
bx /
b11 .
b11 -
b11 ,
b11 +
b11 *
1)
0(
0'
b11 &
b11 %
b11 $
1#
bx "
0!
$end
#1
13
0#
b1 :
1(
0)
1'
#2
0'
#3
b1 1
b1 8
b1 <
b1 U
16
03
14
b1001 E
b1001 K
b1001 `
b1001 b
b11 G
b11 L
b11 \
b10 :
b11 D
b11 Y
b11 _
b11 e
1'
#4
0'
#5
b11011 E
b11011 K
b11011 `
b11011 b
b1 2
b1 9
b1 ;
b1 R
b1001 G
b1001 L
b1001 \
b0 1
b0 8
b0 <
b0 U
b10 0
b10 7
b10 =
b10 [
04
15
b11 :
b1001 "
b1001 /
b1001 >
b1001 F
b1001 X
b1001 ^
b1001 c
1'
#6
0'
#7
b1001 E
b1001 K
b1001 `
b1001 b
b11 G
b11 L
b11 \
b10 2
b10 9
b10 ;
b10 R
b0 0
b0 7
b0 =
b0 [
14
05
b100 :
b11011 J
b11011 W
b11011 ]
b11011 a
1'
#8
0'
#9
b1001 H
b1001 M
b1001 V
b11011 G
b11011 L
b11011 \
b100100 E
b100100 K
b100100 `
b100100 b
b0 2
b0 9
b0 ;
b0 R
b10 1
b10 8
b10 <
b10 U
b11 0
b11 7
b11 =
b11 [
06
04
15
b101 :
1'
#10
0'
#11
b11 2
b11 9
b11 ;
b11 R
b11 H
b11 M
b11 V
b0 1
b0 8
b0 <
b0 U
14
b100111 E
b100111 K
b100111 `
b100111 b
05
b100100 G
b100100 L
b100100 \
b110 :
b100100 J
b100100 W
b100100 ]
b100100 a
1'
#12
0'
#13
1!
b110 E
b110 K
b110 `
b110 b
b11 G
b11 L
b11 \
b0 2
b0 9
b0 ;
b0 R
b0 0
b0 7
b0 =
b0 [
04
b111 :
b100111 "
b100111 /
b100111 >
b100111 F
b100111 X
b100111 ^
b100111 c
1'
